elasticache_auto_discovery/__init__.py
elasticache_auto_discovery-1.0.0.dist-info/DESCRIPTION.rst
elasticache_auto_discovery-1.0.0.dist-info/METADATA
elasticache_auto_discovery-1.0.0.dist-info/RECORD
elasticache_auto_discovery-1.0.0.dist-info/WHEEL
elasticache_auto_discovery-1.0.0.dist-info/metadata.json
elasticache_auto_discovery-1.0.0.dist-info/top_level.txt
