Metadata-Version: 1.1
Name: elasticache-auto-discovery
Version: 1.0.0
Summary: AWS ElastiCache Auto Discovery Client for Python
Home-page: https://github.com/studio-ousia/elasticache-auto-discovery
Author: Studio Ousia
Author-email: admin@ousia.jp
License: Copyright 2013 Studio Ousia
